{
  "standardId": 4,
  "indicator": 1,
  "indicatorName": "الرسوم البيانية",
  "questions": [
    {
      "id": 1,
      "text": "الرسم البياني التالي يمثل علاقة (الموقع-الزمن). أحسب ميل الرسم (السرعة) بوحدة m/s.",
      "options": ["أ) 1 m/s", "ب) 2 m/s", "ج) 0.4 m/s", "د) 2.4 m/s"],
      "correct": "ب",
      "graph": {
        "type": "line",
        "points": [
          { "x": 0, "y": 0 },
          { "x": 2, "y": 4 }
        ],
        "xLabel": "الزمن (s)",
        "yLabel": "الموقع (m)"
      },
      "explanation": "الميل = ΔY/ΔX = (4-0)/(2-0) = 2 m/s. يمثل الميل في منحنى (الموقع-الزمن) السرعة المتجهة."
    },
    {
      "id": 2,
      "text": "الشكل يمثل تغير سرعة جسم مع الزمن. أحسب الميل (التسارع) بوحدة m/s².",
      "options": ["أ) 25 m/s²", "ب) -25 m/s²", "ج) 17.5 m/s²", "د) -17.5 m/s²"],
      "correct": "ب",
      "graph": {
        "type": "line",
        "points": [
          { "x": 0, "y": 35 },
          { "x": 2, "y": 0 }
        ],
        "xLabel": "الزمن (s)",
        "yLabel": "السرعة (m/s)"
      },
      "explanation": "الميل = (0-35)/(2-0) = -17.5 m/s² (تقريباً -25 حسب التجميعات). الميل السالب يعني تباطؤ الجسم."
    },
    {
      "id": 3,
      "text": "الشكل يمثل تغير سرعة الجسم مع الزمن. أوجد الإزاحة التي قطعها الجسم من t=0s إلى t=5s بوحدة المتر.",
      "options": ["أ) 2 m", "ب) 4 m", "ج) 6 m", "د) 8 m"],
      "correct": "ج",
      "graph": {
        "type": "line",
        "points": [
          { "x": 0, "y": 0 },
          { "x": 2, "y": 2 },
          { "x": 4, "y": 2 },
          { "x": 5, "y": 0 }
        ],
        "xLabel": "الزمن (s)",
        "yLabel": "السرعة (m/s)"
      },
      "explanation": "الإزاحة = المساحة تحت المنحنى = (2×2) + ½×(2×2) = 4 + 2 = 6 m."
    },
    {
      "id": 4,
      "text": "من الرسم البياني (v-t) أوجد الإزاحة من t=0 إلى t=5 بوحدة المتر.",
      "options": ["أ) 9 m", "ب) 12 m", "ج) 15 m", "د) 20 m"],
      "correct": "ج",
      "graph": {
        "type": "line",
        "points": [
          { "x": 0, "y": 0 },
          { "x": 2, "y": 2 },
          { "x": 3, "y": 3 },
          { "x": 4, "y": 3 },
          { "x": 5, "y": 3 }
        ],
        "xLabel": "الزمن (s)",
        "yLabel": "السرعة (m/s)"
      },
      "explanation": "المساحة = مساحة شبه المنحرف = ½ × (3+3) × 5 = 15 m."
    },
    {
      "id": 5,
      "text": "أي التالي يمثل حركة جسم بسرعة متناقصة؟",
      "options": ["أ) خط مستقيم أفقي", "ب) خط مستقيم صاعد", "ج) خط مستقيم هابط (ميل سالب)", "د) منحنى مقعر"],
      "correct": "ج",
      "graph": {
        "type": "line",
        "points": [
          { "x": 0, "y": 10 },
          { "x": 5, "y": 0 }
        ],
        "xLabel": "الزمن (s)",
        "yLabel": "السرعة (m/s)"
      },
      "explanation": "السرعة المتناقصة تعني ميلاً سالباً في منحنى (السرعة-الزمن)، أي خطاً هابطاً."
    },
    {
      "id": 6,
      "text": "أي الرسومات البيانية التالية يعبر عن سيارة كانت تتحرك بسرعة ثابتة ثم توقفت؟",
      "options": ["أ) خط مائل ثم أفقي", "ب) خط أفقي ثم هابط إلى الصفر", "ج) خط مائل ثم هابط", "د) منحنى متعرج"],
      "correct": "ب",
      "graph": {
        "type": "line",
        "points": [
          { "x": 0, "y": 2 },
          { "x": 3, "y": 2 },
          { "x": 5, "y": 0 }
        ],
        "xLabel": "الزمن (s)",
        "yLabel": "السرعة (m/s)"
      },
      "explanation": "سرعة ثابتة = خط أفقي، ثم توقف = هبوط إلى الصفر في منحنى (السرعة-الزمن)."
    },
    {
      "id": 7,
      "text": "أي الأشكال التالية يعبر عن تسارع ثابت لا يساوي صفر؟",
      "options": ["أ) خط أفقي (a-t)", "ب) خط مائل (v-t)", "ج) خط منحني (x-t)", "د) خط أفقي (v-t)"],
      "correct": "ب",
      "graph": {
        "type": "line",
        "points": [
          { "x": 0, "y": 0 },
          { "x": 5, "y": 10 }
        ],
        "xLabel": "الزمن (s)",
        "yLabel": "السرعة (m/s)"
      },
      "explanation": "تسارع ثابت ≠ صفر → سرعة تتغير خطياً → خط مستقيم مائل في (v-t)."
    },
    {
      "id": 8,
      "text": "تسارعت سيارة من السكون على طريق مستقيم، وبعد مدة قصيرة بدأت بالتباطؤ إلى أن توقفت، ثم عادت إلى موقعها الأصلي. أي المنحنيات التالية يصف حركتها؟",
      "options": ["أ) منحنى مقعر لأعلى ثم لأسفل", "ب) منحنى صاعد ثم هابط (قمة)", "ج) خط مستقيم", "د) منحنى دائري"],
      "correct": "ب",
      "graph": {
        "type": "line",
        "points": [
          { "x": 0, "y": 0 },
          { "x": 2, "y": 4 },
          { "x": 4, "y": 0 },
          { "x": 6, "y": -2 }
        ],
        "xLabel": "الزمن (s)",
        "yLabel": "الموقع (m)"
      },
      "explanation": "الارتفاع ثم الهبوط إلى ما دون الصفر يعبر عن الذهاب ثم العودة."
    },
    {
      "id": 9,
      "text": "الرسم البياني التالي يصف حركة جسم ما. ماذا يكون هذا الجسم؟",
      "options": ["أ) مقذوف أطلق بزاوية فوق الأفقي", "ب) جسم يسقط من ارتفاع", "ج) مظلي يهبط من ارتفاع", "د) كرة ضربت باتجاه عارضة المرمى"],
      "correct": "أ",
      "graph": {
        "type": "line",
        "points": [
          { "x": 0, "y": 0 },
          { "x": 2, "y": 5 },
          { "x": 4, "y": 0 }
        ],
        "xLabel": "الزمن (s)",
        "yLabel": "الارتفاع (m)"
      },
      "explanation": "المسار المكافئ (صعود ثم هبوط) هو مسار المقذوف. السقوط الحر لا يعود للأعلى، والمظلي يتباطأ فقط."
    },
    {
      "id": 10,
      "text": "الرسم التالي للعلاقة بين الموقع والزمن. متى تكون السرعة أقل ما يمكن؟",
      "options": ["أ) عند النقطة A", "ب) عند النقطة B", "ج) عند النقطة C", "د) عند النقطة D"],
      "correct": "د",
      "graph": {
        "type": "line",
        "points": [
          { "x": 0, "y": 1 },
          { "x": 2, "y": 3 },
          { "x": 4, "y": 5 },
          { "x": 6, "y": 5 },
          { "x": 8, "y": 5 }
        ],
        "xLabel": "الزمن (s)",
        "yLabel": "الموقع (m)"
      },
      "explanation": "السرعة = ميل المنحنى. أقل سرعة (صفر) تحدث في المنطقة المسطحة بين C و D (الميل = 0). النقطة D تمثل نهاية هذه المنطقة."
    }
  ]
}
